nydok/__init__.py
nydok/cli.py
nydok/exception.py
nydok/gitlab.py
nydok/markdown_ext/__init__.py
nydok/markdown_ext/markdown_nydok.py
nydok/markdown_ext/nydok.css
nydok/plugin/__init__.py
nydok/plugin/junit.py
nydok/plugin/plugin.py
nydok/plugin/specification.py
nydok/plugin/specsmanager.py
nydok/plugin/testcase.py
nydok/report.py
nydok/schema.py
nydok-0.8.4.dist-info/LICENSE
nydok-0.8.4.dist-info/METADATA
nydok-0.8.4.dist-info/WHEEL
nydok-0.8.4.dist-info/entry_points.txt
nydok-0.8.4.dist-info/RECORD
