Metadata-Version: 2.3
Name: nydok
Version: 0.8.4
Summary: Documentation and specification testing framework
License: MIT
Author: Nykode Therapeutics
Author-email: insaid@nykode.com
Requires-Python: >=3.10,<4.0
Classifier: License :: OSI Approved :: MIT License
Classifier: Programming Language :: Python :: 3
Classifier: Programming Language :: Python :: 3.10
Classifier: Programming Language :: Python :: 3.11
Classifier: Programming Language :: Python :: 3.12
Classifier: Programming Language :: Python :: 3.13
Requires-Dist: PyYAML (>=6.0)
Requires-Dist: click (>=8.0.0)
Requires-Dist: lxml (>=4.8.0)
Requires-Dist: pytest (>=6.2.5)
Requires-Dist: requests (>=2.28.1)
